{"Training Loss": 25.374110603332518, "_timestamp": 1718209874.377373, "_runtime": 1497.2995100021362, "_step": 90, "Testing Loss": 24.803146362304688, "Spike Animation": {"_type": "video-file", "sha256": "d356af9bdb7ce42999dfa44d6d5359f860e65b9bfff419c802cdfa7b4e276288", "size": 172613, "path": "media/videos/Spike Animation_90_d356af9bdb7ce42999df.gif"}, "Test Loss": 24.803146362304688, "Results Grid": {"_type": "image-file", "sha256": "03a7b036e1722edb014eb118dc2bac75ee0fc6c3a10a77cdcc252bca34929113", "size": 35679, "path": "media/images/Results Grid_90_03a7b036e1722edb014e.png", "format": "png", "width": 864, "height": 720}, "Input Raster": {"_type": "image-file", "sha256": "ba42b9635f2b4a3e69f0a73722c1d27127aaeb8758c80bfa2c3e2a2891fa2685", "size": 29600, "path": "media/images/Input Raster_90_ba42b9635f2b4a3e69f0.png", "format": "png", "width": 720, "height": 360}, "Output Raster": {"_type": "image-file", "sha256": "a2674cad9ab79a48a1e4983ddd4e03c6e628f7ac3077b62ad07c02757faa4226", "size": 27219, "path": "media/images/Output Raster_90_a2674cad9ab79a48a1e4.png", "format": "png", "width": 720, "height": 360}, "_wandb": {"runtime": 1496}}