{"Training Loss": 15749.7615234375, "_timestamp": 1718345806.1763027, "_runtime": 1271.8485786914825, "_step": 90, "Testing Loss": 15682.78583984375, "Spike Animation": {"_type": "video-file", "sha256": "f31c7284b16b47edb8d9d14800a77c75225349a0fdae58f3bff2b3dad8fd29e0", "size": 167896, "path": "media/videos/Spike Animation_90_f31c7284b16b47edb8d9.gif"}, "Test Loss": 15682.78583984375, "Results Grid": {"_type": "image-file", "sha256": "582b7069455511663c19a7502832c03f72f1f8716dd7b67f884e52e05deebcd5", "size": 52375, "path": "media/images/Results Grid_90_582b7069455511663c19.png", "format": "png", "width": 864, "height": 720}, "Input Raster": {"_type": "image-file", "sha256": "32cfcd0d0b93754b130e3953fd278a534be57ea43bb1b518a3918ee2f809a173", "size": 86851, "path": "media/images/Input Raster_90_32cfcd0d0b93754b130e.png", "format": "png", "width": 720, "height": 360}, "Output Raster": {"_type": "image-file", "sha256": "e06c8c4b2a194fc310839182257a11b50a4072f12bd362fac1c357fe4ad9a686", "size": 69395, "path": "media/images/Output Raster_90_e06c8c4b2a194fc31083.png", "format": "png", "width": 720, "height": 360}, "_wandb": {"runtime": 1272}}