{"Training Loss": 0.04432388022542, "_timestamp": 1718457547.5074537, "_runtime": 1448.0513806343079, "_step": 855, "Testing Loss": 0.04532775655388832, "Spike Animation": {"_type": "video-file", "sha256": "78107f5a32303a4717c74954da5cd50bc9d61d3dbc15c614ab3e87e08098bf1d", "size": 65020, "path": "media/videos/Spike Animation_855_78107f5a32303a4717c7.gif"}, "Test Loss": 0.04532775655388832, "Results Grid": {"_type": "image-file", "sha256": "b373960fd581dd378f17b3efbd3eaecefeb898d43769d7d3c8035c282dfbc33a", "size": 34287, "path": "media/images/Results Grid_855_b373960fd581dd378f17.png", "format": "png", "width": 864, "height": 720}, "t-SNE": {"_type": "image-file", "sha256": "a25c431bca0cf9983fcf288360738379741adbee9fd906d5c008b46d455a0f8a", "size": 24486, "path": "media/images/t-SNE_855_a25c431bca0cf9983fcf.png", "format": "png", "width": 720, "height": 432}, "Input Raster": {"_type": "image-file", "sha256": "4ead5360bd08c195a4f12c545d1b54a8d00d671d4b72e3b46461c355c2d0b997", "size": 19660, "path": "media/images/Input Raster_855_4ead5360bd08c195a4f1.png", "format": "png", "width": 720, "height": 360}, "Output Raster": {"_type": "image-file", "sha256": "46af458925f745a7469c48c1ba0f7742e796128a1395c6b4d40a4f46b992d958", "size": 15667, "path": "media/images/Output Raster_855_46af458925f745a7469c.png", "format": "png", "width": 720, "height": 360}, "_wandb": {"runtime": 1450}}