{"Training Loss": 0.21622688472270965, "_timestamp": 1718702142.152896, "_runtime": 1472.4623589515686, "_step": 90, "Testing Loss": 0.20469079166650772, "Spike Animation": {"_type": "video-file", "sha256": "f16c9ba10f8217f2a2d3c1e65a5762e349a843d764767f83018b5e72133a1a1c", "size": 81118, "path": "media/videos/Spike Animation_90_f16c9ba10f8217f2a2d3.gif"}, "Test Loss": 0.20469079166650772, "Results Grid": {"_type": "image-file", "sha256": "884d40c03fd8597ae66cd44f9a698dd1109a6c684dbb4321b8f69d3bfc23da2c", "size": 32530, "path": "media/images/Results Grid_90_884d40c03fd8597ae66c.png", "format": "png", "width": 864, "height": 720}, "UMAP": {"_type": "image-file", "sha256": "710605238200f42a8a9c01d08ef5ea28bcb37fbdd9962a866859be81ab12623a", "size": 62240, "path": "media/images/UMAP_90_710605238200f42a8a9c.png", "format": "png", "width": 720, "height": 432}, "Input Raster": {"_type": "image-file", "sha256": "9729508fc0f33af222216ef3df2a66ab1527363b2c66f611425dd01ceccfd4d0", "size": 19841, "path": "media/images/Input Raster_90_9729508fc0f33af22221.png", "format": "png", "width": 720, "height": 360}, "Output Raster": {"_type": "image-file", "sha256": "6fde8d6b79ee261badee1416206fb7080845d516268d4df16d338b45ce515e74", "size": 17639, "path": "media/images/Output Raster_90_6fde8d6b79ee261badee.png", "format": "png", "width": 720, "height": 360}, "_wandb": {"runtime": 1471}}